mgolddepthlib/__init__.py
mgolddepthlib/wp.py
mgolddepthlib/model/__init__.py
mgolddepthlib/model/marigold_pipeline.py
mgolddepthlib/model/rgb_encoder.py
mgolddepthlib/model/stacked_depth_AE.py
mgolddepthlib/util/__init__.py
mgolddepthlib/util/batchsize.py
mgolddepthlib/util/ensemble.py
mgolddepthlib/util/flow_estimation.py
mgolddepthlib/util/image_util.py
mgolddepthlib/util/seed_all.py
mgolddepthlib-0.2.2.dist-info/LICENSE
mgolddepthlib-0.2.2.dist-info/METADATA
mgolddepthlib-0.2.2.dist-info/WHEEL
mgolddepthlib-0.2.2.dist-info/top_level.txt
mgolddepthlib-0.2.2.dist-info/RECORD
